mura/__init__.py
mura/callbacks.py
mura/data.py
mura/lightning.py
mura/schema.py
mura/train_support.py
mura/version.py
mura-0.2.20.dist-info/METADATA
mura-0.2.20.dist-info/WHEEL
mura-0.2.20.dist-info/top_level.txt
mura-0.2.20.dist-info/RECORD
