Metadata-Version: 2.4
Name: mura
Version: 0.2.20
Summary: WandB, Git, and run-table integration for ML++ / eliminating workflow unevenness
Author-email: Akhil Sadam <sadam.akhil@gmail.com>
Requires-Python: >=3.10
Requires-Dist: wandb>=0.20.1
Requires-Dist: gitpython>=3.1.44
Requires-Dist: numpy>=2.0.0
Requires-Dist: lightning>=2.5.1
Requires-Dist: torch>=2.4.1
Requires-Dist: einops>=0.8.0
Requires-Dist: tqdm>=4.66.5
Requires-Dist: matplotlib>=3.7.1
Requires-Dist: pyyaml>=6.0.2
Requires-Dist: pydantic>=2.11.5
Requires-Dist: toml>=0.10.2
Requires-Dist: omegaconf>=2.3.0
Requires-Dist: pynvml>=12.0.0
